LICENCE
black_nb.py
black_nb-0.1.0.dist-info/entry_points.txt
black_nb-0.1.0.dist-info/WHEEL
black_nb-0.1.0.dist-info/METADATA
black_nb-0.1.0.dist-info/RECORD
